iggy_py-0.4.0.dist-info/METADATA
iggy_py-0.4.0.dist-info/WHEEL
iggy_py-0.4.0.dist-info/licenses/LICENSE
iggy_py-0.4.0.dist-info/licenses/NOTICE
iggy_py/__init__.py
iggy_py/__init__.pyi
iggy_py/py.typed
iggy_py/iggy_py.cpython-311-aarch64-linux-gnu.so
iggy_py-0.4.0.dist-info/RECORD
