Metadata-Version: 2.4
Name: iggy_py
Version: 0.4.0
Classifier: Programming Language :: Rust
Classifier: Programming Language :: Python :: Implementation :: CPython
Classifier: Programming Language :: Python :: Implementation :: PyPy
Requires-Dist: pytest ; extra == 'testing'
Requires-Dist: pytest-asyncio ; extra == 'testing'
Requires-Dist: testcontainers[docker] ; extra == 'testing'
Requires-Dist: maturin ; extra == 'testing'
Provides-Extra: testing
License-File: LICENSE
License-File: NOTICE
Summary: Apache Iggy is the persistent message streaming platform written in Rust, supporting QUIC, TCP and HTTP transport protocols, capable of processing millions of messages per second.
Author: Dario Lencina Talarico <darioalessandrolencina@gmail.com>
Author-email: Dario Lencina Talarico <darioalessandrolencina@gmail.com>
License: Apache-2.0
Requires-Python: >=3.7
Project-URL: Source Code, https://github.com/iggy-rs/iggy
